ocifit/__init__.py
ocifit/cache.py
ocifit/defaults.py
ocifit/guts.py
ocifit/logger.py
ocifit/schema.py
ocifit/version.py
ocifit/client/__init__.py
ocifit/client/compat.py
ocifit/compat/__init__.py
ocifit/compat/client.py
ocifit/compat/dockerfile.py
ocifit/parsers/__init__.py
ocifit/parsers/base.py
ocifit/parsers/gemini.py
ocifit/parsers/nfd.py
ocifit/parsers/software.py
ocifit/utils/__init__.py
ocifit/utils/docker.py
ocifit/utils/fileio.py
ocifit/utils/terminal.py
ocifit-0.0.1.dist-info/LICENSE
ocifit-0.0.1.dist-info/METADATA
ocifit-0.0.1.dist-info/NOTICE
ocifit-0.0.1.dist-info/WHEEL
ocifit-0.0.1.dist-info/entry_points.txt
ocifit-0.0.1.dist-info/top_level.txt
ocifit-0.0.1.dist-info/RECORD
