Metadata-Version: 2.2
Name: ocifit
Version: 0.0.1
Summary: Extract and assess compatibility of container images
Home-page: https://github.com/compspec/ocifit
Author: Vanessa Sochat
Author-email: vsoch@users.noreply.github.com
Maintainer: Vanessa Sochat
License: LICENSE
Keywords: docker,containers,introspection,opencontainers,compatibility
Classifier: Intended Audience :: Science/Research
Classifier: Intended Audience :: Developers
Classifier: License :: OSI Approved :: MIT License
Classifier: Programming Language :: C
Classifier: Programming Language :: Python
Classifier: Topic :: Software Development
Classifier: Topic :: Scientific/Engineering
Classifier: Operating System :: Unix
Classifier: Programming Language :: Python :: 3.11
License-File: LICENSE
License-File: NOTICE
Requires-Dist: protobuf>=5.29.3
Requires-Dist: google-generativeai>=0.8.5
Provides-Extra: all
Requires-Dist: protobuf>=5.29.3; extra == "all"
Requires-Dist: google-generativeai>=0.8.5; extra == "all"
Requires-Dist: pytest>=4.6.2; extra == "all"
Dynamic: author
Dynamic: author-email
Dynamic: classifier
Dynamic: description
Dynamic: description-content-type
Dynamic: home-page
Dynamic: keywords
Dynamic: license
Dynamic: maintainer
Dynamic: provides-extra
Dynamic: requires-dist
Dynamic: summary
